platon_env/__init__.py
platon_env/chain.py
platon_env/genesis.py
platon_env/node.py
platon_env/base/__init__.py
platon_env/base/host.py
platon_env/base/process.py
platon_env/base/service.py
platon_env/base/supervisor/__init__.py
platon_env/base/supervisor/supervisor.conf
platon_env/base/supervisor/supervisor.py
platon_env/factory/__init__.py
platon_env/factory/factory.py
platon_env/utils/__init__.py
platon_env/utils/executor.py
platon_env/utils/utils.py
platon_env/utils/bls/__init__.py
platon_env/utils/bls/bls12381.py
platon_env/utils/bls/ec.py
platon_env/utils/bls/fields.py
platon_env/utils/bls/hash_to_field.py
platon_env/utils/bls/hd_keys.py
platon_env/utils/bls/hkdf.py
platon_env/utils/bls/impl-test.py
platon_env/utils/bls/op_swu_g2.py
platon_env/utils/bls/pairing.py
platon_env/utils/bls/private_key.py
platon_env/utils/bls/schemes.py
platon_env/utils/bls/util.py
platon_env/utils/key/__init__.py
platon_env/utils/key/keytool.py
platon_env/utils/key/bin/keytool
platon_env/utils/key/bin/keytool.exe
platon_env-1.3.5.dist-info/LICENSE
platon_env-1.3.5.dist-info/METADATA
platon_env-1.3.5.dist-info/WHEEL
platon_env-1.3.5.dist-info/top_level.txt
platon_env-1.3.5.dist-info/RECORD
