Metadata-Version: 2.1
Name: platon-env
Version: 1.3.5
Summary: Common library to deployment platon chain
Home-page: https://github.com/shinnng/platon-env
Author: Shinnng
Author-email: shinnng@outlook.com
License: MIT
Keywords: platon
Platform: UNKNOWN
Classifier: Development Status :: 4 - Beta
Classifier: Intended Audience :: Developers
Classifier: License :: OSI Approved :: MIT License
Classifier: Natural Language :: English
Classifier: Programming Language :: Python :: 3
Classifier: Programming Language :: Python :: 3.6
Classifier: Programming Language :: Python :: 3.7
Classifier: Programming Language :: Python :: 3.8
License-File: LICENSE
Requires-Dist: dacite (>=1.6.0)
Requires-Dist: fabric (>=2.6.0)
Requires-Dist: loguru (>=0.5.3)
Requires-Dist: paramiko (>=2.8.0)
Requires-Dist: ruamel.base (>=1.0.0)
Requires-Dist: rwlock (>=0.0.7)
Provides-Extra: platon-env
Requires-Dist: dacite (>=1.6.0) ; extra == 'platon-env'
Requires-Dist: fabric (>=2.6.0) ; extra == 'platon-env'
Requires-Dist: loguru (>=0.5.3) ; extra == 'platon-env'
Requires-Dist: paramiko (>=2.8.0) ; extra == 'platon-env'
Requires-Dist: ruamel.base (>=1.0.0) ; extra == 'platon-env'
Requires-Dist: rwlock (>=0.0.7) ; extra == 'platon-env'
